<map>
<!-- EFEITOS PADRÕES DO HABBO HOTEL VÃO DO 1 AO 187 -->
<effect id="dance.1" lib="efeitos/Dance1" type="dance" revision="59200"/>
<effect id="dance.3" lib="efeitos/Dance3" type="dance" revision="59200"/>
<effect id="dance.2" lib="efeitos/Dance2" type="dance" revision="59200"/>
<effect id="dance.4" lib="efeitos/Dance4" type="dance" revision="59200"/>
<effect id="1" lib="efeitos/Spotlight" type="fx" revision="59200"/>
<effect id="2" lib="efeitos/Hoverboard" type="fx" revision="59200"/>
<effect id="3" lib="efeitos/UFOblue" type="fx" revision="59200"/>
<effect id="4" lib="efeitos/Twinkle" type="fx" revision="59200"/>
<effect id="5" lib="efeitos/Torch" type="fx" revision="59220"/>
<effect id="6" lib="efeitos/Jetpack" type="fx" revision="59200"/>
<effect id="7" lib="efeitos/Butterflies" type="fx" revision="59200"/>
<effect id="8" lib="efeitos/Fireflies" type="fx" revision="59200"/>
<effect id="9" lib="efeitos/Love" type="fx" revision="59200"/>
<effect id="10" lib="efeitos/Flies" type="fx" revision="59200"/>
<effect id="11" lib="efeitos/XRay" type="fx" revision="59200"/>
<effect id="12" lib="efeitos/Ice" type="fx" revision="59200"/>
<effect id="13" lib="efeitos/Ghost" type="fx" revision="59200"/>
<effect id="14" lib="efeitos/HoverboardPink" type="fx" revision="59200"/>
<effect id="15" lib="efeitos/HoverboardYellow" type="fx" revision="59200"/>
<effect id="16" lib="efeitos/Microphone" type="fx" revision="59220"/>
<effect id="17" lib="efeitos/UFOpink" type="fx" revision="59200"/>
<effect id="18" lib="efeitos/UFOyellow" type="fx" revision="59200"/>
<effect id="19" lib="efeitos/Carpolice" type="fx" revision="59200"/>
<effect id="20" lib="efeitos/Carambulance" type="fx" revision="59200"/>
<effect id="21" lib="efeitos/Cardollar" type="fx" revision="59200"/>
<effect id="22" lib="efeitos/Cartopfuel" type="fx" revision="59200"/>
<effect id="23" lib="efeitos/TotemMan" type="fx" revision="59200"/>
<effect id="24" lib="efeitos/TotemMerdragon" type="fx" revision="59200"/>
<effect id="25" lib="efeitos/TotemEagle" type="fx" revision="59200"/>
<effect id="26" lib="efeitos/TotemMix" type="fx" revision="59220"/>
<effect id="27" lib="efeitos/Viking" type="fx" revision="59220"/>
<effect id="28" lib="efeitos/Splash" type="fx" revision="59200"/>
<effect id="29" lib="efeitos/Swimming" type="fx" revision="59200"/>
<effect id="30" lib="efeitos/Wade" type="fx" revision="59200"/>
<effect id="31" lib="efeitos/Cheetos" type="fx" revision="59220"/>
<effect id="32" lib="efeitos/DespicableMe" type="fx" revision="59200"/>
<effect id="33" lib="efeitos/BBRed" type="fx" revision="59200"/>
<effect id="34" lib="efeitos/BBgreen" type="fx" revision="59200"/>
<effect id="35" lib="efeitos/BBblue" type="fx" revision="59200"/>
<!-- ;D -->
<effect id="36" lib="efeitos/BByellow" type="fx" revision="59200"/>
<effect id="37" lib="efeitos/Wadeinswamp" type="fx" revision="59200"/>
<effect id="38" lib="efeitos/IceSkatingboys" type="fx" revision="59220"/>
<effect id="39" lib="efeitos/IceSkatinggirls" type="fx" revision="59220"/>
<effect id="40" lib="efeitos/ESred" type="fx" revision="59220"/>
<effect id="41" lib="efeitos/ESgreen" type="fx" revision="59220"/>
<effect id="42" lib="efeitos/ESblue" type="fx" revision="59220"/>
<effect id="43" lib="efeitos/ESyellow" type="fx" revision="59220"/>
<effect id="44" lib="efeitos/Sims" type="fx" revision="59200"/>
<effect id="45" lib="efeitos/TaggedIceSkatingboys" type="fx" revision="59200"/>
<effect id="46" lib="efeitos/TaggedIceSkatinggirls" type="fx" revision="59200"/>
<effect id="47" lib="efeitos/Megamind" type="fx" revision="59200"/>
<effect id="48" lib="efeitos/CarDoggy" type="fx" revision="59200"/>
<effect id="49" lib="efeitos/ESredUntouchable" type="fx" revision="59200"/>
<effect id="50" lib="efeitos/ESgreenUntouchable" type="fx" revision="59200"/>
<effect id="51" lib="efeitos/ESblueUntouchable" type="fx" revision="59200"/>
<effect id="52" lib="efeitos/ESyellowUntouchable" type="fx" revision="59200"/>
<effect id="53" lib="efeitos/Easterchicks" type="fx" revision="59200"/>
<effect id="54" lib="efeitos/Easterbunny" type="fx" revision="59200"/>
<effect id="55" lib="efeitos/RollerSkatingboys" type="fx" revision="59220"/>
<effect id="56" lib="efeitos/RollerSkatinggirls" type="fx" revision="59220"/>
<effect id="57" lib="efeitos/TaggedRollerSkatingboys" type="fx" revision="59200"/>
<effect id="58" lib="efeitos/TaggedRollerSkatinggirls" type="fx" revision="59200"/>
<effect id="59" lib="efeitos/SunnyDelight" type="fx" revision="59200"/>
<effect id="60" lib="efeitos/Rango" type="fx" revision="59200"/>
<effect id="61" lib="efeitos/DisneyChannelEffect1" type="fx" revision="59200"/>
<effect id="62" lib="efeitos/DisneyChannelEffect2" type="fx" revision="59200"/>
<effect id="63" lib="efeitos/DisneyChannelEffect3" type="fx" revision="59200"/>
<effect id="64" lib="efeitos/Candle" type="fx" revision="59220"/>
<effect id="65" lib="efeitos/mobile0800" type="fx" revision="59220"/>
<!-- =D -->
<effect id="66" lib="efeitos/DisneyWizardsofWaverly" type="fx" revision="59220"/>
<effect id="67" lib="efeitos/RioParrot" type="fx" revision="59200"/>
<effect id="68" lib="efeitos/eastertagging" type="fx" revision="59200"/>
<effect id="69" lib="efeitos/Volkswagen" type="fx" revision="59200"/>
<effect id="70" lib="efeitos/KungfuPanda" type="fx" revision="59200"/>
<effect id="71" lib="efeitos/Skateboard1" type="fx" revision="59200"/>
<effect id="72" lib="efeitos/Skateboard2" type="fx" revision="59200"/>
<effect id="73" lib="efeitos/ChupaChups" type="fx" revision="59200"/>
<effect id="74" lib="efeitos/Lei1" type="fx" revision="59200"/>
<effect id="75" lib="efeitos/Lei2" type="fx" revision="59200"/>
<effect id="76" lib="efeitos/Lei3" type="fx" revision="59200"/>
<effect id="77" lib="efeitos/Riding" type="fx" revision="59220"/>
<effect id="78" lib="efeitos/Perry" type="fx" revision="59200"/>
<effect id="79" lib="efeitos/AlienMask" type="fx" revision="59200"/>
<effect id="80" lib="efeitos/GiantMouth" type="fx" revision="59200"/>
<effect id="81" lib="efeitos/SwampCreatureMask" type="fx" revision="59200"/>
<effect id="82" lib="efeitos/InkBlotMask" type="fx" revision="59200"/>
<effect id="83" lib="efeitos/MimeMask" type="fx" revision="59200"/>
<effect id="84" lib="efeitos/MummyMask" type="fx" revision="59200"/>
<effect id="85" lib="efeitos/PumpkinMask" type="fx" revision="59200"/>
<effect id="86" lib="efeitos/ScarecrowMask" type="fx" revision="59200"/>
<effect id="87" lib="efeitos/WolfMask" type="fx" revision="59200"/>
<!-- .-. -->
<effect id="88" lib="efeitos/ZombieMask" type="fx" revision="59200"/>
<effect id="89" lib="efeitos/BackKnife" type="fx" revision="59200"/>
<effect id="90" lib="efeitos/ButteryflyWings1" type="fx" revision="59200"/>
<effect id="91" lib="efeitos/FairyWings1" type="fx" revision="59200"/>
<effect id="92" lib="efeitos/GhostSheet" type="fx" revision="59200"/>
<effect id="93" lib="efeitos/Headless" type="fx" revision="59200"/>
<effect id="94" lib="efeitos/LiisuTruck" type="fx" revision="59200"/>
<effect id="95" lib="efeitos/Snowwarred" type="fx" revision="59200"/>
<effect id="96" lib="efeitos/Snowwarblue" type="fx" revision="59200"/>
<effect id="97" lib="efeitos/Snowboardplch" type="fx" revision="59660"/>
<effect id="98" lib="efeitos/SnowstormCrosshair" type="fx" revision="59200"/>
<effect id="99" lib="efeitos/Niko" type="fx" revision="59220"/>
<effect id="100" lib="efeitos/Dragon" type="fx" revision="59200"/>
<effect id="101" lib="efeitos/BangGun" type="fx" revision="59220"/>
<effect id="102" lib="efeitos/Staff" type="fx" revision="59200"/>
<effect id="103" lib="efeitos/RidingSaddle2" type="fx" revision="59220"/>
<effect id="104" lib="efeitos/Pie" type="fx" revision="59200"/>
<effect id="105" lib="efeitos/Dubbelfrisss" type="fx" revision="59200"/>
<effect id="106" lib="efeitos/BlueTorch" type="fx" revision="59220"/>
<effect id="107" lib="efeitos/PlastoPodChair" type="fx" revision="59200"/>
<effect id="108" lib="efeitos/Ninjadisappear" type="fx" revision="59200"/>
<effect id="109" lib="efeitos/Medal1" type="fx" revision="59200"/>
<effect id="110" lib="efeitos/Medal2" type="fx" revision="59200"/>
<effect id="111" lib="efeitos/Medal3" type="fx" revision="59200"/>
<effect id="112" lib="efeitos/SpiderMan" type="fx" revision="59200"/>
<effect id="113" lib="efeitos/Raincloud" type="fx" revision="59200"/>
<effect id="114" lib="efeitos/StrongArms" type="fx" revision="59200"/>
<effect id="115" lib="efeitos/Ringmaster" type="fx" revision="59200"/>
<effect id="116" lib="efeitos/Fly" type="fx" revision="59200"/>
<!-- POR QUE, SE NÃO... -->
<effect id="117" lib="efeitos/Executioner" type="fx" revision="59220"/>
<effect id="118" lib="efeitos/Evilclown" type="fx" revision="59200"/>
<effect id="119" lib="efeitos/DarkAlienMask" type="fx" revision="59200"/>
<effect id="120" lib="efeitos/GiantMouth2" type="fx" revision="59254"/>
<effect id="121" lib="efeitos/SwampCreatureMask2" type="fx" revision="59254"/>
<effect id="122" lib="efeitos/InkBlotMask2" type="fx" revision="59254"/>
<effect id="123" lib="efeitos/MimeMask2" type="fx" revision="59254"/>
<effect id="124" lib="efeitos/Mummy2Mask" type="fx" revision="59200"/>
<effect id="125" lib="efeitos/FrostPumpkinMask" type="fx" revision="59200"/>
<effect id="126" lib="efeitos/ScarecrowMask2" type="fx" revision="59254"/>
<effect id="127" lib="efeitos/EvilWolfMask" type="fx" revision="59200"/>
<effect id="128" lib="efeitos/ZombieMask2" type="fx" revision="59254"/>
<effect id="129" lib="efeitos/BackKnife2" type="fx" revision="59254"/>
<effect id="130" lib="efeitos/ButteryflyWings2" type="fx" revision="59254"/>
<effect id="131" lib="efeitos/FairyWings2" type="fx" revision="59254"/>
<effect id="132" lib="efeitos/GlowingGhostSheet" type="fx" revision="59200"/>
<effect id="133" lib="efeitos/Headless2" type="fx" revision="59256"/>
<effect id="134" lib="efeitos/SnakeBody" type="fx" revision="59220"/>
<effect id="135" lib="efeitos/PuppetMaster" type="fx" revision="59200"/>
<effect id="136" lib="efeitos/BackwalkingShoes" type="fx" revision="59220"/>
<effect id="137" lib="efeitos/GoldSpotlight" type="fx" revision="59200"/>
<effect id="138" lib="efeitos/GoldenGlasses" type="fx" revision="59200"/>
<effect id="139" lib="efeitos/GoldMicrophone" type="fx" revision="59220"/>
<effect id="140" lib="efeitos/HabnamDance" type="fx" revision="59200"/>
<effect id="141" lib="efeitos/Flowermask" type="fx" revision="59200"/>
<effect id="142" lib="efeitos/Goatmask" type="fx" revision="59200"/>
<effect id="143" lib="efeitos/Feathermask1" type="fx" revision="59200"/>
<effect id="144" lib="efeitos/Feathermask2" type="fx" revision="59200"/>
<effect id="145" lib="efeitos/Feathermask3" type="fx" revision="59200"/>
<effect id="146" lib="efeitos/Feathermask4" type="fx" revision="59200"/>
<effect id="147" lib="efeitos/Peacock1Mask" type="fx" revision="59200"/>
<effect id="148" lib="efeitos/Peacock2Mask" type="fx" revision="59200"/>
<effect id="149" lib="efeitos/Peacock3Mask" type="fx" revision="59200"/>
<effect id="150" lib="efeitos/Peacock4Mask" type="fx" revision="59200"/>
<effect id="151" lib="efeitos/Goatmask2" type="fx" revision="59200"/>
<effect id="152" lib="efeitos/Goatmask3" type="fx" revision="59200"/>
<effect id="153" lib="efeitos/Flowermask2" type="fx" revision="59200"/>
<effect id="154" lib="efeitos/MassiveEgg" type="fx" revision="59200"/>
<effect id="155" lib="efeitos/bcrystal" type="fx" revision="59200"/>
<effect id="156" lib="efeitos/gcrystal" type="fx" revision="59200"/>
<effect id="157" lib="efeitos/Pimple" type="fx" revision="59200"/>
<!-- VAI SE FUDER .-.' -->
<effect id="158" lib="efeitos/Pinata" type="fx" revision="59200"/>
<effect id="159" lib="efeitos/Barrel" type="fx" revision="59200"/>
<effect id="160" lib="efeitos/PirateCaptain" type="fx" revision="59220"/>
<effect id="161" lib="efeitos/PirateCrew" type="fx" revision="59220"/>
<effect id="162" lib="efeitos/PirateSword" type="fx" revision="59200"/>
<effect id="163" lib="efeitos/HeadOnTheGround" type="fx" revision="59200"/>
<effect id="164" lib="efeitos/PirateGun" type="fx" revision="59200"/>
<effect id="165" lib="efeitos/SpinningThumbsUp" type="fx" revision="59200"/>
<effect id="166" lib="efeitos/Goblin" type="fx" revision="59200"/>
<effect id="167" lib="efeitos/Mutant" type="fx" revision="59200"/>
<effect id="168" lib="efeitos/SpinningHeats" type="fx" revision="59200"/>
<effect id="169" lib="efeitos/Slimed" type="fx" revision="59200"/>
<effect id="170" lib="efeitos/Duck" type="fx" revision="61749"/>
<effect id="171" lib="efeitos/SpaceBunny" type="fx" revision="59200"/>
<effect id="172" lib="efeitos/RedViking" type="fx" revision="59220"/>
<effect id="173" lib="efeitos/GreenViking" type="fx" revision="59220"/>
<effect id="174" lib="efeitos/HoverboardGreen" type="fx" revision="59200"/>
<effect id="175" lib="efeitos/RedAirplane" type="fx" revision="59200"/>
<effect id="176" lib="efeitos/BlueAirplane" type="fx" revision="59200"/>
<effect id="177" lib="efeitos/TarandFeather" type="fx" revision="59200"/>
<effect id="178" lib="efeitos/Ambassador" type="fx" revision="59200"/>
<effect id="179" lib="efeitos/Luchador" type="fx" revision="59200"/>
<effect id="180" lib="efeitos/DayoftheDead" type="fx" revision="59200"/>
<effect id="181" lib="efeitos/DayoftheDead2" type="fx" revision="59200"/>
<effect id="182" lib="efeitos/CyberpunkGun" type="fx" revision="59200"/>
<effect id="183" lib="efeitos/FossilHammer" type="fx" revision="59200"/>
<effect id="184" lib="efeitos/SplashEvil" type="fx" revision="59791"/>
<effect id="185" lib="efeitos/SwimEvil" type="fx" revision="59733"/>
<effect id="186" lib="efeitos/MagicWand" type="fx" revision="60704"/>
<effect id="187" lib="efeitos/Bot" type="fx" revision="60559"/>
<!-- EFEITOS EFEITOS CUSTOMS VÃO DO 188 AO 196 -->
<effect id="188" lib="efeitos/CameraBot" type="fx" revision="61736"/>
<effect id="189" lib="efeitos/MobileDisco" type="fx" revision="61750"/>
<effect id="190" lib="efeitos/MobileDisco2" type="fx" revision="61750"/>
<effect id="191" lib="efeitos/Hoverplank" type="fx" revision="61800"/>
<effect id="192" lib="efeitos/WateringCan" type="fx" revision="61861"/>
<effect id="193" lib="efeitos/TrampolineJump" type="fx" revision="62089"/>
<effect id="194" lib="efeitos/Treadmill" type="fx" revision="62149"/>
<effect id="195" lib="efeitos/CrossTrainer" type="fx" revision="62175"/>
<effect id="196" lib="efeitos/LightTorch" type="fx" revision="62175"/>
<effect id="199" lib="efeitos/Turtleride" type="fx" revision="63413"/>
<effect id="202" lib="efeitos/SintStaf" type="fx" revision="160116"/>
<effect id="218" lib="efeitos/Pumpkin" type="fx" revision="061016"/>
<!-- EFEITOS EFEITOS CUSTOMS VÃO DO 500 AO 548/550/551/ -->
<effect id="490" lib="efeitos/Peog" type="fx" revision="61749"/>
<effect id="491" lib="efeitos/clb" type="fx" revision="60559"/>
<effect id="492" lib="efeitos/cpl" type="fx" revision="60559"/>
<effect id="493" lib="efeitos/frz" type="fx" revision="60559"/>
<effect id="494" lib="efeitos/gay" type="fx" revision="60559"/>
<effect id="496" lib="efeitos/MarioKartGreen" type="fx" revision="040616"/>
<effect id="497" lib="efeitos/MarioKartPink" type="fx" revision="040616"/>
<effect id="498" lib="efeitos/MarioKartOrange" type="fx" revision="62457"/>
<effect id="499" lib="efeitos/MarioKartGold" type="fx" revision="62457"/>
<effect id="500" lib="efeitos/BigSpn" type="fx" revision="62175"/>
<effect id="501" lib="efeitos/SmallS" type="fx" revision="62175"/>
<effect id="502" lib="efeitos/BigJmp" type="fx" revision="62175"/>
<effect id="503" lib="efeitos/SmallJ" type="fx" revision="62175"/>
<effect id="504" lib="efeitos/Hoverplan1" type="fx" revision="62175"/>
<effect id="505" lib="efeitos/Hoverplan2" type="fx" revision="62175"/>
<effect id="506" lib="efeitos/Hoverplan3" type="fx" revision="62175"/>
<effect id="507" lib="efeitos/TrampolineTest" type="fx" revision="62175"/>
<effect id="508" lib="efeitos/Hoverplan4" type="fx" revision="62175"/>
<effect id="509" lib="efeitos/Trampolineb360" type="fx" revision="62175"/>
<effect id="510" lib="efeitos/Sable1" type="fx" revision="62175"/>
<effect id="511" lib="efeitos/Sable2" type="fx" revision="62175"/>
<effect id="512" lib="efeitos/Sable3" type="fx" revision="62175"/>
<effect id="513" lib="efeitos/Sable4" type="fx" revision="62175"/>
<effect id="514" lib="efeitos/Sable5" type="fx" revision="62175"/>
<effect id="515" lib="efeitos/Sable6" type="fx" revision="62175"/>
<effect id="516" lib="efeitos/Sable7" type="fx" revision="62175"/>
<effect id="517" lib="efeitos/AusentesBenjywHt" type="fx" revision="62175"/>
<effect id="518" lib="efeitos/PinkPlaneBW" type="fx" revision="62175"/>
<effect id="519" lib="efeitos/GrenPlaneBW" type="fx" revision="62175"/>
<effect id="520" lib="efeitos/YelwPlaneBW" type="fx" revision="62175"/>
<effect id="521" lib="efeitos/OrgnPlaneBW" type="fx" revision="62175"/>
<effect id="522" lib="efeitos/FlechitaOldSchOl" type="fx" revision="62175"/>
<effect id="523" lib="efeitos/Pgo" type="fx" revision="62175"/>
<effect id="524" lib="efeitos/LightTorc2" type="fx" revision="62175"/>
<effect id="525" lib="efeitos/LightTorc3" type="fx" revision="62175"/>
<effect id="526" lib="efeitos/LightTorc4" type="fx" revision="62175"/>
<effect id="527" lib="efeitos/LightTorc5" type="fx" revision="62175"/>
<effect id="528" lib="efeitos/LightTorc6" type="fx" revision="62175"/>
<effect id="529" lib="efeitos/Ambul" type="fx" revision="62175"/>
<effect id="530" lib="efeitos/Bat" type="fx" revision="62175"/>
<effect id="531" lib="efeitos/BlackFlame" type="fx" revision="62175"/>
<effect id="532" lib="efeitos/BlackpunkGun" type="fx" revision="62175"/>
<effect id="533" lib="efeitos/Bus" type="fx" revision="62175"/>
<effect id="534" lib="efeitos/Carstaff" type="fx" revision="62175"/>
<effect id="535" lib="efeitos/Cuf" type="fx" revision="62175"/>
<effect id="536" lib="efeitos/CyberstunGun" type="fx" revision="62175"/>
<effect id="537" lib="efeitos/DrugLeafOk" type="fx" revision="62175"/>
<effect id="538" lib="efeitos/FishingRod" type="fx" revision="62175"/>
<effect id="539" lib="efeitos/HoloRPGoldGun" type="fx" revision="62175"/>
<effect id="540" lib="efeitos/HoloRP666Gun" type="fx" revision="62175"/>
<effect id="541" lib="efeitos/HoloRPGun" type="fx" revision="62175"/>
<effect id="542" lib="efeitos/HoloRPPinkGun" type="fx" revision="62175"/>
<effect id="543" lib="efeitos/HoloRPPolice" type="fx" revision="62175"/>
<effect id="544" lib="efeitos/MagicDildo" type="fx" revision="62175"/>
<effect id="545" lib="efeitos/MedicalKit" type="fx" revision="62175"/>
<effect id="546" lib="efeitos/PickaxeRok" type="fx" revision="62175"/>
<effect id="547" lib="efeitos/Pika" type="fx" revision="62175"/>
<effect id="548" lib="efeitos/PinkFlame" type="fx" revision="62175"/>
<effect id="549" lib="efeitos/Locutorzera" type="fx" revision="62175"/>
<effect id="550" lib="efeitos/bbwibb" type="fx" revision="62175"/>
<effect id="551" lib="efeitos/blackb" type="fx" revision="62175"/>
<effect id="568" lib="efeitos/WibboHomer" type="fx" revision="55555"/>
<effect id="470" lib="efeitos/Smokeweed" type="fx" revision="59220"/>
<effect id="768" lib="efeitos/FSpinn" type="fx" revision="55555"/>
<!-- EFEITOS EFEITOS CUSTOMS VÃO DO 986 AO 999 -->
<effect id="986" lib="efeitos/Stupeficium" type="fx" revision="90000"/>
<effect id="987" lib="efeitos/Sectumsempra" type="fx" revision="90000"/>
<effect id="988" lib="efeitos/ProtegoHorribilis" type="fx" revision="90000"/>
<effect id="989" lib="efeitos/Protego" type="fx" revision="90000"/>
<effect id="990" lib="efeitos/Plasma" type="fx" revision="90000"/>
<effect id="991" lib="efeitos/Periculum" type="fx" revision="90000"/>
<effect id="992" lib="efeitos/Nimbus2001" type="fx" revision="90000"/>
<effect id="993" lib="efeitos/Nimbus2000" type="fx" revision="90000"/>
<effect id="994" lib="efeitos/Lumos" type="fx" revision="90000"/>
<effect id="995" lib="efeitos/Incarceramus" type="fx" revision="90000"/>
<effect id="996" lib="efeitos/Finge" type="fx" revision="90000"/>
<effect id="997" lib="efeitos/Coerceo" type="fx" revision="90000"/>
<effect id="998" lib="efeitos/AvadaKedavra" type="fx" revision="90000"/>
<effect id="999" lib="efeitos/Adultero" type="fx" revision="90000"/>
<effect id="1000" lib="efeitos/acc_0cc_des" type="fx" revision="62457"/>  
<effect id="1002" lib="efeitos/acc_shirt_go" type="fx" revision="62457"/>  
<effect id="1004" lib="efeitos/acc_pants_9srt" type="fx" revision="62457"/>  
<effect id="1005" lib="efeitos/molhand" type="fx" revision="62457"/>  
<effect id="2000" lib="efeitos/BCS1erp" type="fx" revision="62457"/>  
<effect id="2001" lib="efeitos/RCS1erp" type="fx" revision="59200"/>  
<effect id="3100" lib="efeitos/mtb_2018s" type="fx" revision="59200"/>  
<effect id="3101" lib="efeitos/mtfg_2018s" type="fx" revision="62457"/>  
<effect id="3103" lib="efeitos/mtr_2018s" type="fx" revision="62457"/>  
<effect id="3104" lib="efeitos/mtg_2018s" type="fx" revision="62457"/>

</map>